<?xml version="1.0" encoding="utf-8"?><HelpTOCNode Title="AVUser Properties" Url="html/6F59F45B.htm"><HelpTOCNode Title="CurrentUser Property " Url="html/B600C45C.htm" /><HelpTOCNode Title="Email Property " Url="html/A9C7B2E2.htm" /><HelpTOCNode Title="IsAnonymous Property " Url="html/B3F9E55F.htm" /><HelpTOCNode Title="IsAuthenticated Property " Url="html/3A3CF555.htm" /><HelpTOCNode Title="MobilePhoneNumber Property " Url="html/2977BCED.htm" /><HelpTOCNode Title="MobilePhoneVerified Property " Url="html/147D24B8.htm" /><HelpTOCNode Title="Password Property " Url="html/8694C3E1.htm" /><HelpTOCNode Title="Query Property " Url="html/C27F985E.htm" /><HelpTOCNode Title="Username Property " Url="html/EF519856.htm" /></HelpTOCNode>